rian/__init__.py
rian/typing.py
rian/base/__init__.py
rian/base/array.py
rian/base/nbase.py
rian/core/__init__.py
rian/core/cli.py
rian/core/dcmeta.py
rian/core/log.py
rian/core/session.py
rian/core/tty.py
rian/core/ws.py
rian/core/ui/__init__.py
rian/core/ui/shell.py
rian/data/testsuite.zip
rian/data/tutorial.zip
rian/dataset/__init__.py
rian/dataset/builder/__init__.py
rian/dataset/builder/plain.py
rian/dataset/classes/__init__.py
rian/dataset/classes/base.py
rian/dataset/commons/__init__.py
rian/dataset/commons/labels/__init__.py
rian/dataset/commons/labels/gene.py
rian/dataset/exports/__init__.py
rian/dataset/exports/archive.py
rian/dataset/exports/image.py
rian/dataset/exports/text.py
rian/dataset/imports/__init__.py
rian/dataset/imports/archive.py
rian/dataset/imports/text.py
rian/math/__init__.py
rian/math/curve.py
rian/math/graph.py
rian/math/matrix.py
rian/math/regress.py
rian/math/stat.py
rian/math/test.py
rian/math/vector.py
rian/model/__init__.py
rian/model/analysis/__init__.py
rian/model/analysis/bayes.py
rian/model/analysis/generic.py
rian/model/analysis/hybrid.py
rian/model/analysis/markov.py
rian/model/builder/__init__.py
rian/model/builder/base.py
rian/model/classes/__init__.py
rian/model/classes/base.py
rian/model/evaluation/__init__.py
rian/model/evaluation/ann.py
rian/model/evaluation/base.py
rian/model/evaluation/dbn.py
rian/model/evaluation/rbm.py
rian/model/exports/__init__.py
rian/model/exports/archive.py
rian/model/exports/image.py
rian/model/imports/__init__.py
rian/model/imports/archive.py
rian/model/morphisms/__init__.py
rian/model/morphisms/ann.py
rian/model/morphisms/base.py
rian/model/morphisms/dbn.py
rian/model/morphisms/rbm.py
rian/network/__init__.py
rian/network/builder/__init__.py
rian/network/builder/layer.py
rian/network/classes/__init__.py
rian/network/classes/base.py
rian/network/classes/layer.py
rian/network/exports/__init__.py
rian/network/exports/archive.py
rian/network/exports/graph.py
rian/network/exports/image.py
rian-0.5.583.dist-info/LICENSE
rian-0.5.583.dist-info/METADATA
rian-0.5.583.dist-info/WHEEL
rian-0.5.583.dist-info/entry_points.txt
rian-0.5.583.dist-info/top_level.txt
rian-0.5.583.dist-info/RECORD
