Metadata-Version: 2.1
Name: rian
Version: 0.5.583
Summary: Enterprise Machine-Learning and Predictive Analytics
Home-page: https://www.frootlab.org/rian
Author: Frootlab Developers
Author-email: contact@frootlab.org
License: GPLv3
Keywords: data-analysis enterprise-data-analysis data-science collaborative-data-science data-visualization machine-learning artificial-intelligence deep-learning probabilistic-graphical-model
Platform: UNKNOWN
Classifier: Development Status :: 2 - Pre-Alpha
Classifier: Intended Audience :: Science/Research
Classifier: License :: OSI Approved :: GNU General Public License v3 (GPLv3)
Classifier: Programming Language :: Python :: 3
Classifier: Programming Language :: Python :: 3.7
Classifier: Operating System :: OS Independent
Classifier: Topic :: Scientific/Engineering :: Artificial Intelligence
Classifier: Topic :: Scientific/Engineering :: Information Analysis
Classifier: Topic :: Database :: Database Engines/Servers
Classifier: Topic :: Software Development :: Libraries :: Python Modules
Requires-Python: >=3.7
Requires-Dist: ipython (>=7.1)
Requires-Dist: matplotlib (>=3.0)
Requires-Dist: networkx (>=2.1)
Requires-Dist: numpy (>=1.15)
Requires-Dist: hup (>=0.9.2)
Requires-Dist: deet (>=0.1.11)
Provides-Extra: gene
Requires-Dist: rpy2 ; extra == 'gene'
Provides-Extra: gui
Requires-Dist: pyside ; extra == 'gui'
